portscaner.py
portscaner-1.34.dist-info/WHEEL
portscaner-1.34.dist-info/METADATA
portscaner-1.34.dist-info/RECORD
