Metadata-Version: 2.1
Name: portscaner
Version: 1.34
Summary: Simple port scanner with progress bar
License: The Unlicensed
Author: AllewKley
Author-email: 100071713+AllewKley@users.noreply.github.com
Requires-Python: >=3.5,<4.0
Classifier: License :: Other/Proprietary License
Classifier: Programming Language :: Python :: 3
Classifier: Programming Language :: Python :: 3.10
Classifier: Programming Language :: Python :: 3.5
Classifier: Programming Language :: Python :: 3.6
Classifier: Programming Language :: Python :: 3.7
Classifier: Programming Language :: Python :: 3.8
Classifier: Programming Language :: Python :: 3.9
